actinia_api/__init__.py
actinia_api/swagger2/__init__.py
actinia_api/swagger2/actinia_core/__init__.py
actinia_api/swagger2/actinia_core/apidocs/api_log_management.py
actinia_api/swagger2/actinia_core/apidocs/download_cache_management.py
actinia_api/swagger2/actinia_core/apidocs/ephemeral_processing_with_export.py
actinia_api/swagger2/actinia_core/apidocs/mapset_management.py
actinia_api/swagger2/actinia_core/apidocs/mapsets.py
actinia_api/swagger2/actinia_core/apidocs/persistent_processing.py
actinia_api/swagger2/actinia_core/apidocs/process_chain_monitoring.py
actinia_api/swagger2/actinia_core/apidocs/process_validation.py
actinia_api/swagger2/actinia_core/apidocs/project_management.py
actinia_api/swagger2/actinia_core/apidocs/raster_export.py
actinia_api/swagger2/actinia_core/apidocs/resource_management.py
actinia_api/swagger2/actinia_core/apidocs/resource_storage_management.py
actinia_api/swagger2/actinia_core/apidocs/user_api_key.py
actinia_api/swagger2/actinia_core/apidocs/user_management.py
actinia_api/swagger2/actinia_core/schemas/__init__.py
actinia_api/swagger2/actinia_core/schemas/api_log_management.py
actinia_api/swagger2/actinia_core/schemas/mapset_management.py
actinia_api/swagger2/actinia_core/schemas/process_chain_monitoring.py
actinia_api/swagger2/actinia_core/schemas/project_management.py
actinia_api/swagger2/actinia_core/schemas/user_api_key.py
actinia_api/swagger2/actinia_grassdata_management_plugin/__init__.py
actinia_api/swagger2/actinia_grassdata_management_plugin/apidocs/map_layer_management.py
actinia_api/swagger2/actinia_grassdata_management_plugin/apidocs/raster_colors.py
actinia_api/swagger2/actinia_grassdata_management_plugin/apidocs/raster_layer.py
actinia_api/swagger2/actinia_grassdata_management_plugin/apidocs/raster_legend.py
actinia_api/swagger2/actinia_grassdata_management_plugin/apidocs/raster_renderer.py
actinia_api/swagger2/actinia_grassdata_management_plugin/apidocs/strds_management.py
actinia_api-3.8.0.dist-info/licenses/LICENSE.txt
actinia_api-3.8.0.dist-info/METADATA
actinia_api-3.8.0.dist-info/WHEEL
actinia_api-3.8.0.dist-info/top_level.txt
actinia_api-3.8.0.dist-info/RECORD
