Metadata-Version: 2.4
Name: actinia-api
Version: 3.8.0
Summary: API description for actinia-core and official plugins.
Author: Anika Weinmann, Carmen Tawalika, Julia Haas, Markus Metz, Markus Neteler, Stefan Blumentrath, Sören Gebbert
Project-URL: Homepage, https://github.com/mundialis/actinia-api
Project-URL: Tutorial, https://mundialis.github.io/actinia_core
Project-URL: API_Docs, https://redocly.github.io/redoc/?url=https://actinia.mundialis.de/latest/swagger.json
Keywords: processing,earth observation,grass gis
Classifier: License :: OSI Approved :: GNU General Public License v3 (GPLv3)
Classifier: Programming Language :: Python :: 3
Requires-Python: >=3.8
License-File: LICENSE.txt
Requires-Dist: flask-restful-swagger-2
Provides-Extra: test
Requires-Dist: setuptools; extra == "test"
Requires-Dist: pytest; extra == "test"
Requires-Dist: ytest-cov; extra == "test"
Dynamic: license-file
